atlas/__init__.py
atlas/__main__.py
atlas/apple_health.py
atlas/cli.py
atlas_db-0.2.11.dist-info/LICENSE
atlas_db-0.2.11.dist-info/METADATA
atlas_db-0.2.11.dist-info/WHEEL
atlas_db-0.2.11.dist-info/entry_points.txt
atlas_db-0.2.11.dist-info/top_level.txt
atlas_db-0.2.11.dist-info/RECORD
