Metadata-Version: 2.1
Name: atlas-db
Version: 0.2.11
Summary: turn apple health export.xml into parquet
Author: Thomas Schranz
License: Apache-2.0
Project-URL: Homepage, https://github.com/atlaslib/atlas
Project-URL: Changelog, https://github.com/atlaslib/atlas/releases
Project-URL: Issues, https://github.com/atlaslib/atlas/issues
Project-URL: CI, https://github.com/atlaslib/atlas/actions
Classifier: License :: OSI Approved :: Apache Software License
Requires-Python: >=3.8
License-File: LICENSE
Requires-Dist: click
Requires-Dist: lxml >=5.2.1
Requires-Dist: polars >=0.20.22
Provides-Extra: test
Requires-Dist: pytest ; extra == 'test'
